autosklearn313/__init__.py
autosklearn313/classifier.py
autosklearn313/regressor.py
autosklearn313-0.1.0.dist-info/METADATA
autosklearn313-0.1.0.dist-info/WHEEL
autosklearn313-0.1.0.dist-info/top_level.txt
autosklearn313-0.1.0.dist-info/RECORD
